topsis.py
Ekaspreet_topsis_102017078-1.0.1.dist-info/LICENSE
Ekaspreet_topsis_102017078-1.0.1.dist-info/METADATA
Ekaspreet_topsis_102017078-1.0.1.dist-info/WHEEL
Ekaspreet_topsis_102017078-1.0.1.dist-info/entry_points.txt
Ekaspreet_topsis_102017078-1.0.1.dist-info/top_level.txt
Ekaspreet_topsis_102017078-1.0.1.dist-info/RECORD
