Metadata-Version: 2.1
Name: Ekaspreet-topsis-102017078
Version: 1.0.1
Summary: A Python package implementing TOPSIS for MCDM
Home-page: https://github.com/Ekaspreet20/Ekaspreet_topsis_102017078
Download-URL: https://github.com/Ekaspreet20/Ekaspreet_topsis_102017078/archive/refs/tags/v_01.tar.gz
Author: Ekaspreet kaur
Author-email: ekaspreet0209@gmail.com
License: MIT
Keywords: python,TOPSIS,MCDM,MCDA,statistics,prescriptive analytics,cli
Classifier: License :: OSI Approved :: MIT License
Classifier: Programming Language :: Python :: 3
Classifier: Programming Language :: Python :: 3.7
License-File: LICENSE
Requires-Dist: numpy
Requires-Dist: pandas
